vserial/__init__.py
vserial/vserial_posix.py
vserial/vserial_win.py
vserial-0.1.2.dist-info/METADATA
vserial-0.1.2.dist-info/WHEEL
vserial-0.1.2.dist-info/licenses/LICENSE
vserial-0.1.2.dist-info/RECORD
