Metadata-Version: 2.4
Name: vserial
Version: 0.1.2
Summary: Virtual serial device library
Project-URL: Repository, https://github.com/seantfish/vserial.git
Author-email: Sean Fish <seantfish@gmail.com>
License-File: LICENSE
Requires-Python: >=3.8
